topsislib/__init__.py
Topsis_Jaskaran_101917129-0.0.13.dist-info/METADATA
Topsis_Jaskaran_101917129-0.0.13.dist-info/WHEEL
Topsis_Jaskaran_101917129-0.0.13.dist-info/top_level.txt
Topsis_Jaskaran_101917129-0.0.13.dist-info/RECORD
